geops/__about__.py
geops/__init__.py
geops/rotation.py
geops/built_in/__init__.py
geops/built_in/bspline.py
geops/built_in/circle_arc.py
geops/built_in/compound_line.py
geops/built_in/compound_surface.py
geops/built_in/compound_volume.py
geops/built_in/define_constant.py
geops/built_in/dummy.py
geops/built_in/ellipse_arc.py
geops/built_in/geometry.py
geops/built_in/line.py
geops/built_in/line_base.py
geops/built_in/line_loop.py
geops/built_in/plane_surface.py
geops/built_in/point.py
geops/built_in/point_base.py
geops/built_in/spline.py
geops/built_in/surface.py
geops/built_in/surface_base.py
geops/built_in/surface_loop.py
geops/built_in/volume.py
geops/built_in/volume_base.py
geops/opencascade/__init__.py
geops/opencascade/ball.py
geops/opencascade/box.py
geops/opencascade/cone.py
geops/opencascade/cylinder.py
geops/opencascade/disk.py
geops/opencascade/geometry.py
geops/opencascade/rectangle.py
geops/opencascade/surface_base.py
geops/opencascade/torus.py
geops/opencascade/volume_base.py
geops/opencascade/wedge.py
geops-0.1.dist-info/LICENSE
geops-0.1.dist-info/METADATA
geops-0.1.dist-info/WHEEL
geops-0.1.dist-info/top_level.txt
geops-0.1.dist-info/RECORD
